faststream_schema_registry/__init__.py
faststream_schema_registry/middleware.py
faststream_schema_registry/registries.py
faststream_schema_registry-0.1.1.dist-info/LICENSE
faststream_schema_registry-0.1.1.dist-info/METADATA
faststream_schema_registry-0.1.1.dist-info/WHEEL
faststream_schema_registry-0.1.1.dist-info/RECORD
