Metadata-Version: 2.3
Name: faststream-schema-registry
Version: 0.1.1
Summary: 
Author: Mark Lovretovich
Author-email: mlovretovich@gmail.com
Requires-Python: >=3.10,<4.0
Classifier: Programming Language :: Python :: 3
Classifier: Programming Language :: Python :: 3.10
Classifier: Programming Language :: Python :: 3.11
Classifier: Programming Language :: Python :: 3.12
Classifier: Programming Language :: Python :: 3.13
Requires-Dist: boto3
Requires-Dist: dataclasses-avroschema[pydantic]
Requires-Dist: faker
Requires-Dist: faststream
Requires-Dist: python-schema-registry-client
